swh/storage/__init__.py
swh/storage/backfill.py
swh/storage/cli.py
swh/storage/common.py
swh/storage/exc.py
swh/storage/fixer.py
swh/storage/in_memory.py
swh/storage/interface.py
swh/storage/metrics.py
swh/storage/migrate_extrinsic_metadata.py
swh/storage/objstorage.py
swh/storage/py.typed
swh/storage/pytest_plugin.py
swh/storage/replay.py
swh/storage/utils.py
swh/storage/writer.py
swh/storage/algos/__init__.py
swh/storage/algos/diff.py
swh/storage/algos/dir_iterators.py
swh/storage/algos/directory.py
swh/storage/algos/discovery.py
swh/storage/algos/origin.py
swh/storage/algos/revisions_walker.py
swh/storage/algos/snapshot.py
swh/storage/api/__init__.py
swh/storage/api/client.py
swh/storage/api/serializers.py
swh/storage/api/server.py
swh/storage/cassandra/__init__.py
swh/storage/cassandra/common.py
swh/storage/cassandra/converters.py
swh/storage/cassandra/cql.py
swh/storage/cassandra/diagram.py
swh/storage/cassandra/migrations.py
swh/storage/cassandra/model.py
swh/storage/cassandra/schema.py
swh/storage/cassandra/storage.py
swh/storage/postgresql/__init__.py
swh/storage/postgresql/converters.py
swh/storage/postgresql/db.py
swh/storage/postgresql/storage.py
swh/storage/proxies/__init__.py
swh/storage/proxies/buffer.py
swh/storage/proxies/filter.py
swh/storage/proxies/record_references.py
swh/storage/proxies/retry.py
swh/storage/proxies/tenacious.py
swh/storage/proxies/validate.py
swh/storage/proxies/blocking/__init__.py
swh/storage/proxies/blocking/cli.py
swh/storage/proxies/blocking/cls.py
swh/storage/proxies/blocking/db.py
swh/storage/proxies/blocking/sql/10-superuser-init.sql
swh/storage/proxies/blocking/sql/30-schema.sql
swh/storage/proxies/blocking/sql/60-indexes.sql
swh/storage/proxies/masking/__init__.py
swh/storage/proxies/masking/cli.py
swh/storage/proxies/masking/cls.py
swh/storage/proxies/masking/db.py
swh/storage/proxies/masking/sql/10-superuser-init.sql
swh/storage/proxies/masking/sql/20-types.sql
swh/storage/proxies/masking/sql/30-schema.sql
swh_storage-4.1.0.dist-info/licenses/AUTHORS
swh_storage-4.1.0.dist-info/licenses/LICENSE
swh_storage-4.1.0.dist-info/METADATA
swh_storage-4.1.0.dist-info/WHEEL
swh_storage-4.1.0.dist-info/entry_points.txt
swh_storage-4.1.0.dist-info/top_level.txt
swh_storage-4.1.0.dist-info/RECORD
