Metadata-Version: 2.4
Name: swh.storage
Version: 4.1.0
Summary: Software Heritage storage manager
Author-email: Software Heritage developers <swh-devel@inria.fr>
Project-URL: Homepage, https://gitlab.softwareheritage.org/swh/devel/swh-storage
Project-URL: Bug Reports, https://gitlab.softwareheritage.org/swh/devel/swh-storage/-/issues
Project-URL: Funding, https://www.softwareheritage.org/donate
Project-URL: Documentation, https://docs.softwareheritage.org/devel/swh-storage/
Project-URL: Source, https://gitlab.softwareheritage.org/swh/devel/swh-storage.git
Classifier: Programming Language :: Python :: 3
Classifier: Intended Audience :: Developers
Classifier: License :: OSI Approved :: GNU General Public License v3 (GPLv3)
Classifier: Operating System :: OS Independent
Classifier: Development Status :: 5 - Production/Stable
Requires-Python: >=3.9
License-File: LICENSE
License-File: AUTHORS
Requires-Dist: backports.entry_points_selectable
Requires-Dist: cassandra-driver!=3.21.0,>=3.19.0
Requires-Dist: click!=8.2.1
Requires-Dist: deprecated
Requires-Dist: flask
Requires-Dist: iso8601
Requires-Dist: mypy_extensions
Requires-Dist: pyasyncore; python_version > "3.12"
Requires-Dist: psycopg
Requires-Dist: psycopg_pool>=3.1
Requires-Dist: redis
Requires-Dist: tenacity>=8.4.2
Requires-Dist: typing-extensions
Requires-Dist: swh.core[db,http]>=4.0.0
Requires-Dist: swh.model>=8.4.0
Requires-Dist: swh.objstorage>=2.2.0
Provides-Extra: testing
Requires-Dist: hypothesis>=3.11.0; extra == "testing"
Requires-Dist: pytest>=8.1; extra == "testing"
Requires-Dist: pytest-mock; extra == "testing"
Requires-Dist: swh.core[testing]>=3.0.0; extra == "testing"
Requires-Dist: swh.model[testing]; extra == "testing"
Requires-Dist: swh.journal[pytest]>=2.0.0; extra == "testing"
Requires-Dist: pytz; extra == "testing"
Requires-Dist: pytest-postgresql; extra == "testing"
Requires-Dist: pytest-redis; extra == "testing"
Requires-Dist: types-confluent-kafka; extra == "testing"
Requires-Dist: types-python-dateutil; extra == "testing"
Requires-Dist: types-pytz; extra == "testing"
Requires-Dist: types-pyyaml; extra == "testing"
Requires-Dist: types-redis; extra == "testing"
Requires-Dist: types-requests; extra == "testing"
Requires-Dist: types-toml; extra == "testing"
Requires-Dist: cassandra-driver!=3.21.0,>=3.19.0; extra == "testing"
Requires-Dist: pyasyncore; python_version > "3.12" and extra == "testing"
Requires-Dist: pytest>=8.1; extra == "testing"
Requires-Dist: pytest-postgresql; extra == "testing"
Requires-Dist: pytest-shared-session-scope; extra == "testing"
Requires-Dist: pytest-xdist; extra == "testing"
Requires-Dist: swh.core[db]; extra == "testing"
Provides-Extra: pytest
Requires-Dist: cassandra-driver!=3.21.0,>=3.19.0; extra == "pytest"
Requires-Dist: pyasyncore; python_version > "3.12" and extra == "pytest"
Requires-Dist: pytest>=8.1; extra == "pytest"
Requires-Dist: pytest-postgresql; extra == "pytest"
Requires-Dist: pytest-shared-session-scope; extra == "pytest"
Requires-Dist: pytest-xdist; extra == "pytest"
Requires-Dist: swh.core[db]; extra == "pytest"
Provides-Extra: journal
Requires-Dist: swh.journal>=1.2; extra == "journal"
Dynamic: license-file
